Metadata-Version: 2.1
Name: panCG
Version: 1.0.2
Summary: An integrative pipeline for family-level super-pangenome analysis across coding and noncoding sequences.
Home-page: https://github.com/rejo27
Author: ltan
Author-email: lei.tan.bio@outlook.com
License: MIT
Keywords: python,panCG,windows,mac,linux
Classifier: Development Status :: 1 - Planning
Classifier: Intended Audience :: Developers
Classifier: Programming Language :: Python :: 3
Classifier: Operating System :: Unix
Classifier: Operating System :: MacOS :: MacOS X
Classifier: Operating System :: Microsoft :: Windows
License-File: LICENSE
Requires-Dist: numpy <2
Requires-Dist: pandas >=2.2.2
Requires-Dist: pyBigWig >=0.3.23
Requires-Dist: pyranges >=0.1.2
Requires-Dist: ete3 >=3.1.3
Requires-Dist: biopython >=1.84
Requires-Dist: networkx >=3.2.1
Requires-Dist: PyYAML >=6.0.2
Requires-Dist: scipy >=1.13.1
Requires-Dist: jcvi >=1.4.21
